manifest_to_helm/__init__.py
manifest_to_helm/reader.py
manifest_to_helm/utils.py
manifest_to_helm-0.1.2.dist-info/LICENSE
manifest_to_helm-0.1.2.dist-info/WHEEL
manifest_to_helm-0.1.2.dist-info/METADATA
manifest_to_helm-0.1.2.dist-info/RECORD
