Metadata-Version: 2.1
Name: manifest-to-helm
Version: 0.1.2
Summary: A helper library to convert Kubernetes YAML manifests to Helm charts
Author: John Carter
Author-email: jfcarter2358@gmail.com
Requires-Python: >=3.8,<4.0
Classifier: Programming Language :: Python :: 3
Classifier: Programming Language :: Python :: 3.10
Classifier: Programming Language :: Python :: 3.8
Classifier: Programming Language :: Python :: 3.9
Requires-Dist: PyYAML (>=6.0,<7.0)
